pyDICOS.so
pydicos-1.3.0.dist-info/WHEEL
pydicos-1.3.0.dist-info/METADATA
pydicos-1.3.0.dist-info/top_level.txt
pydicos-1.3.0.dist-info/RECORD
pydicos-1.3.0.dist-info/LICENSE.txt
pydicos/__init__.py
pydicos/version.py
pydicos/_dicosio.py
pydicos/utils/__init__.py
pydicos/utils/time.py
pydicos/_loaders/DX.py
pydicos/_loaders/ATR.py
pydicos/_loaders/__init__.py
pydicos/_loaders/TDR.py
pydicos/_loaders/CT.py
