Metadata-Version: 2.1
Name: pydicos
Version: 1.3.0
Summary: pyDICOS is a python package for working with DICOS files.
Home-page: https://github.com/Auxilia-tech/pydicos
Download-URL: https://github.com/Auxilia-tech/pydicos/
Author: Louis Combaldieu
Author-email: louis.combaldieu@auxilia-tech.com
License: MIT
Keywords: DICOS,Digital,Imaging,Communications,Security
Classifier: Development Status :: 3 - Alpha
Classifier: Intended Audience :: Developers
Classifier: Topic :: Software Development :: Build Tools
Classifier: License :: OSI Approved :: MIT License
Classifier: Programming Language :: Python :: 3
Classifier: Programming Language :: Python :: 3.7
Classifier: Programming Language :: Python :: 3.8
Classifier: Programming Language :: Python :: 3.9
Classifier: Programming Language :: Python :: 3.10
Classifier: Programming Language :: Python :: 3.11
Requires-Python: >=3
License-File: LICENSE.txt
Requires-Dist: numpy
